maestro/__init__.py
maestro/channel.py
maestro/constants.py
maestro/device.py
maestro/enums.py
maestro/exceptions.py
maestro/structs.py
maestro/tests/__init__.py
maestro/tests/test_device.py
maestro_servo-0.2.0.dist-info/WHEEL
maestro_servo-0.2.0.dist-info/METADATA
maestro_servo-0.2.0.dist-info/RECORD
